myMainlib/__init__.py
myMainlib/myfunctions.py
myMainlib-0.1.0.dist-info/METADATA
myMainlib-0.1.0.dist-info/WHEEL
myMainlib-0.1.0.dist-info/top_level.txt
myMainlib-0.1.0.dist-info/RECORD
